get_pypi_latest_version/__init__.py
get_pypi_latest_version/main.py
get_pypi_latest_version-0.1.0.dist-info/LICENSE
get_pypi_latest_version-0.1.0.dist-info/METADATA
get_pypi_latest_version-0.1.0.dist-info/WHEEL
get_pypi_latest_version-0.1.0.dist-info/entry_points.txt
get_pypi_latest_version-0.1.0.dist-info/top_level.txt
get_pypi_latest_version-0.1.0.dist-info/RECORD
