Metadata-Version: 2.1
Name: get-pypi-latest-version
Version: 0.1.0
Summary: Get the latest version of the specified python package name in the pypi.
Home-page: https://github.com/SWHL/GetPyPiLatestVersion
Author: SWHL
Author-email: liekkaskono@163.com
License: Apache-2.0
Download-URL: https://github.com/SWHL/GetPyPiLatestVersion.git
Keywords: pypi,latest_version
Platform: Any
Classifier: Programming Language :: Python :: 3 :: Only
Classifier: Programming Language :: Python :: 3.6
Classifier: Programming Language :: Python :: 3.7
Classifier: Programming Language :: Python :: 3.8
Classifier: Programming Language :: Python :: 3.9
Classifier: Programming Language :: Python :: 3.10
Classifier: Programming Language :: Python :: 3.11
Classifier: Programming Language :: Python :: 3.12
Requires-Python: >=3.6,<3.13
Requires-Dist: requests >=2.28.1
Requires-Dist: packaging
